procbench/__init__.py
procbench/__main__.py
procbench/cli.py
procbench/errors.py
procbench/metrics.py
procbench/monitor.py
procbench/output.py
procbench/runner.py
procbench/schema.py
procbench/summary.py
procbench/testcase.py
procbench/templates/html_template.html
procbench/templates/html_template_prompt.md
procbench-0.1.1.dist-info/METADATA
procbench-0.1.1.dist-info/WHEEL
procbench-0.1.1.dist-info/entry_points.txt
procbench-0.1.1.dist-info/top_level.txt
procbench-0.1.1.dist-info/RECORD
