Metadata-Version: 2.4
Name: procbench
Version: 0.1.1
Summary: Process Benchmarking Tool
Requires-Python: >=3.12
Requires-Dist: click>=8.3.1
Requires-Dist: psutil>=7.2.1
